MANIFEST.in
README.rst
setup.py
kvm/__init__.py
kvm/kvm.json
kvm.egg-info/PKG-INFO
kvm.egg-info/SOURCES.txt
kvm.egg-info/dependency_links.txt
kvm.egg-info/requires.txt
kvm.egg-info/top_level.txt