Metadata-Version: 1.1
Name: kvm
Version: 1.1.0
Summary: An API for managing KVM host.
Home-page: UNKNOWN
Author: François Ménabé
Author-email: francois.menabe@gmail.com
License: MIT License
Keywords: python,kvm,unix,virsh
Platform: UNKNOWN
Classifier: License :: OSI Approved :: MIT License
Classifier: Development Status :: 3 - Alpha
Classifier: Intended Audience :: System Administrators
Classifier: Programming Language :: Python
Classifier: Programming Language :: Python :: 2.7
Classifier: Programming Language :: Python :: 3.4
Classifier: Programming Language :: Python :: 3.5
Classifier: Operating System :: Unix
Classifier: Topic :: System :: Systems Administration
